django_rest_framework_hmac-0.3.1.dist-info/DESCRIPTION.rst
django_rest_framework_hmac-0.3.1.dist-info/LICENSE.txt
django_rest_framework_hmac-0.3.1.dist-info/METADATA
django_rest_framework_hmac-0.3.1.dist-info/RECORD
django_rest_framework_hmac-0.3.1.dist-info/WHEEL
django_rest_framework_hmac-0.3.1.dist-info/metadata.json
django_rest_framework_hmac-0.3.1.dist-info/top_level.txt
rest_framework_hmac/__init__.py
rest_framework_hmac/apps.py
rest_framework_hmac/authentication.py
rest_framework_hmac/client.py
rest_framework_hmac/models.py
rest_framework_hmac/hmac_key/__init__.py
rest_framework_hmac/hmac_key/admin.py
rest_framework_hmac/hmac_key/apps.py
rest_framework_hmac/hmac_key/models.py
rest_framework_hmac/hmac_key/migrations/0001_initial.py
rest_framework_hmac/hmac_key/migrations/__init__.py
