Metadata-Version: 2.0
Name: django-rest-framework-hmac
Version: 0.3.1
Summary: HMAC Authentication for the django-rest-framework
Home-page: https://github.com/aaronlelevier/django-rest-framework-hmac
Author: Aaron Lelevier
Author-email: aaron.lelevier@gmail.com
License: BSD
Platform: UNKNOWN
Classifier: Development Status :: 2 - Pre-Alpha
Classifier: Environment :: Web Environment
Classifier: Framework :: Django
Classifier: Framework :: Django :: 2.0
Classifier: Intended Audience :: Developers
Classifier: License :: OSI Approved :: BSD License
Classifier: Operating System :: OS Independent
Classifier: Programming Language :: Python
Classifier: Programming Language :: Python :: 3
Classifier: Programming Language :: Python :: 3.6
Classifier: Topic :: Internet :: WWW/HTTP
Requires-Python: >=3.6
